dataspree/zwo_asi_python_bindings/ASICamera2.dll
dataspree/zwo_asi_python_bindings/__about__.py
dataspree/zwo_asi_python_bindings/__init__.py
dataspree/zwo_asi_python_bindings/asi.c
dataspree/zwo_asi_python_bindings/asi.cp311-win_amd64.pyd
dataspree/zwo_asi_python_bindings/asi.pyx
dataspree/zwo_asi_python_bindings/pywrapper.c
dataspree/zwo_asi_python_bindings/pywrapper.cp311-win_amd64.pyd
dataspree/zwo_asi_python_bindings/pywrapper.pyx
dataspree_zwo_asi_python_bindings-1.0.1.dist-info/licenses/LICENSE.txt
vendor/ASICamera2.h
vendor/hello.h
vendor/linux/build.sh
vendor/linux/armv6/libASICamera2.a
vendor/linux/armv6/libASICamera2.so
vendor/linux/armv6/libASICamera2.so.1.36
vendor/linux/armv7/libASICamera2.a
vendor/linux/armv7/libASICamera2.so
vendor/linux/armv7/libASICamera2.so.1.36
vendor/linux/armv8/libASICamera2.a
vendor/linux/armv8/libASICamera2.so
vendor/linux/armv8/libASICamera2.so.1.36
vendor/linux/mac/libASICamera2.a
vendor/linux/mac/libASICamera2.dylib
vendor/linux/mac/libASICamera2.dylib.1.36
vendor/linux/x64/cwrapper.pxd
vendor/linux/x64/libASICamera2.a
vendor/linux/x64/libASICamera2.so
vendor/linux/x64/libASICamera2.so.1.36
vendor/linux/x64/libhello.so
vendor/linux/x86/libASICamera2.a
vendor/linux/x86/libASICamera2.so
vendor/linux/x86/libASICamera2.so.1.36
vendor/windows/x64/ASICamera2.dll
vendor/windows/x64/ASICamera2.lib
vendor/windows/x86/ASICamera2.dll
vendor/windows/x86/ASICamera2.lib
dataspree_zwo_asi_python_bindings-1.0.1.dist-info/METADATA
dataspree_zwo_asi_python_bindings-1.0.1.dist-info/WHEEL
dataspree_zwo_asi_python_bindings-1.0.1.dist-info/top_level.txt
dataspree_zwo_asi_python_bindings-1.0.1.dist-info/RECORD
