Metadata-Version: 2.4
Name: dataspree_zwo_asi_python_bindings
Version: 1.0.1
Summary: Python bindings for the ZWO ASI library
Author-email: Data Spree GmbH <julius.huelsmann@data-spree.com>
License: Copyright (c) 2026 Data Spree GmbH
Project-URL: Homepage, https://www.data-spree.com/
Project-URL: Documentation, https://github.com/dataspree/dataspree_zwo_asi_python_bindings.git
Project-URL: Repository, https://github.com/dataspree/dataspree_zwo_asi_python_bindings.git
Keywords: zwo_asi_python_bindings,dataspree
Requires-Python: <3.15,>=3.10
License-File: LICENSE.txt
Dynamic: license-file
